cli/__init__.py
cli/main.py
cli/commands/__init__.py
cli/commands/binding.py
cli/commands/exchange.py
cli/commands/queue.py
cli/commands/shared.py
cli/formatters/__init__.py
cli/formatters/json.py
cli/formatters/table.py
config/__init__.py
config/logging.py
config/settings.py
logging/__init__.py
logging/config.py
logging/correlation.py
logging/formatters.py
logging/logger.py
logging/processors.py
logging/redaction.py
logging/rotation.py
logging/handlers/__init__.py
logging/handlers/console.py
logging/handlers/file.py
logging/handlers/rabbitmq.py
mcp_server/__init__.py
mcp_server/openapi/__init__.py
mcp_server/operations/__init__.py
mcp_server/schemas/__init__.py
mcp_server/tools/__init__.py
mcp_server/utils/__init__.py
mcp_server/utils/logging.py
mcp_server/vector_db/__init__.py
models/__init__.py
models/log_config.py
models/log_entry.py
rabbitmq_mcp_connection/__init__.py
rabbitmq_mcp_connection/connection/__init__.py
rabbitmq_mcp_connection/connection/aio_pika_compat.py
rabbitmq_mcp_connection/connection/config.py
rabbitmq_mcp_connection/connection/exceptions.py
rabbitmq_mcp_connection/connection/health.py
rabbitmq_mcp_connection/connection/manager.py
rabbitmq_mcp_connection/connection/monitor.py
rabbitmq_mcp_connection/connection/pool.py
rabbitmq_mcp_connection/contracts/__init__.py
rabbitmq_mcp_connection/contracts/connection-operations.json
rabbitmq_mcp_connection/logging/__init__.py
rabbitmq_mcp_connection/logging/config.py
rabbitmq_mcp_connection/logging/sanitizer.py
rabbitmq_mcp_connection/schemas/__init__.py
rabbitmq_mcp_connection/schemas/connection.py
rabbitmq_mcp_connection/schemas/mcp.py
rabbitmq_mcp_connection/schemas/retry.py
rabbitmq_mcp_connection/tools/__init__.py
rabbitmq_mcp_connection/tools/call_id.py
rabbitmq_mcp_connection/tools/contracts.py
rabbitmq_mcp_connection/tools/get_id.py
rabbitmq_mcp_connection/tools/search_ids.py
rabbitmq_mcp_server/__init__.py
rabbitmq_mcp_server/__main__.py
rabbitmq_mcp_server/config/__init__.py
rabbitmq_mcp_server-3.2.0.dist-info/METADATA
rabbitmq_mcp_server-3.2.0.dist-info/WHEEL
rabbitmq_mcp_server-3.2.0.dist-info/entry_points.txt
rabbitmq_mcp_server-3.2.0.dist-info/licenses/LICENSE
rabbitmq_mcp_server-3.2.0.dist-info/RECORD
